files/__init__.py
files/files.py
backwork_backup_files-0.3.1.dist-info/LICENSE
backwork_backup_files-0.3.1.dist-info/METADATA
backwork_backup_files-0.3.1.dist-info/WHEEL
backwork_backup_files-0.3.1.dist-info/entry_points.txt
backwork_backup_files-0.3.1.dist-info/top_level.txt
backwork_backup_files-0.3.1.dist-info/RECORD
