Metadata-Version: 2.1
Name: backwork-backup-files
Version: 0.3.1
Summary: Backwork plug-in for file backups.
Home-page: https://github.com/IBM/backwork-backup-files
Author: Leons Petrazickis
Author-email: leonsp@ca.ibm.com
License: Apache 2
Classifier: Development Status :: 3 - Alpha
Classifier: Environment :: Console
Classifier: Intended Audience :: Developers
Classifier: Intended Audience :: System Administrators
Classifier: Operating System :: POSIX :: Linux
Classifier: License :: OSI Approved :: Apache Software License
Classifier: Programming Language :: Python :: 2.7
Classifier: Programming Language :: Python :: 2 :: Only
Classifier: Topic :: System :: Archiving :: Backup
Classifier: Topic :: Utilities
License-File: LICENSE
Requires-Dist: backwork
